{
  "config": {
    "configFile": "C:\\Users\\lavanya.gorrela\\OneDrive - Feuji Software Solutions Pvt Ltd\\Automation\\Playwright_new\\reports\\playwright.config.js",
    "rootDir": "C:/Users/lavanya.gorrela/OneDrive - Feuji Software Solutions Pvt Ltd/Automation/Playwright_new/reports/tests",
    "forbidOnly": false,
    "fullyParallel": true,
    "globalSetup": null,
    "globalTeardown": null,
    "globalTimeout": 0,
    "grep": {},
    "grepInvert": null,
    "maxFailures": 0,
    "metadata": {
      "actualWorkers": 2
    },
    "preserveOutput": "always",
    "reporter": [
      [
        "line",
        null
      ],
      [
        "list",
        null
      ],
      [
        "dot",
        null
      ],
      [
        "html",
        null
      ],
      [
        "json",
        {
          "outputFile": "result.json"
        }
      ],
      [
        "junit",
        {
          "outputFile": "result.xml"
        }
      ],
      [
        "C:\\Users\\lavanya.gorrela\\OneDrive - Feuji Software Solutions Pvt Ltd\\Automation\\Playwright_new\\reports\\node_modules\\allure-playwright\\dist\\index.js",
        null
      ]
    ],
    "reportSlowTests": {
      "max": 5,
      "threshold": 15000
    },
    "quiet": false,
    "projects": [
      {
        "outputDir": "C:/Users/lavanya.gorrela/OneDrive - Feuji Software Solutions Pvt Ltd/Automation/Playwright_new/reports/test-results",
        "repeatEach": 1,
        "retries": 0,
        "id": "chromium",
        "name": "chromium",
        "testDir": "C:/Users/lavanya.gorrela/OneDrive - Feuji Software Solutions Pvt Ltd/Automation/Playwright_new/reports/tests",
        "testIgnore": [],
        "testMatch": [
          "**/*.@(spec|test).?(c|m)[jt]s?(x)"
        ],
        "timeout": 30000
      }
    ],
    "shard": null,
    "updateSnapshots": "missing",
    "version": "1.43.1",
    "workers": 4,
    "webServer": null
  },
  "suites": [
    {
      "title": "example.spec.js",
      "file": "example.spec.js",
      "column": 0,
      "line": 0,
      "specs": [
        {
          "title": "Test-10::webdriveruniversity ",
          "ok": true,
          "tags": [],
          "tests": [
            {
              "timeout": 30000,
              "annotations": [],
              "expectedStatus": "passed",
              "projectId": "chromium",
              "projectName": "chromium",
              "results": [
                {
                  "workerIndex": 0,
                  "status": "passed",
                  "duration": 2607,
                  "errors": [],
                  "stdout": [],
                  "stderr": [],
                  "retry": 0,
                  "startTime": "2024-04-15T05:05:38.867Z",
                  "attachments": []
                }
              ],
              "status": "expected"
            }
          ],
          "id": "dd9b2edffe9b7501040c-422771156a3302174e58",
          "file": "example.spec.js",
          "line": 48,
          "column": 6
        },
        {
          "title": "Test-11::demoqa ",
          "ok": true,
          "tags": [],
          "tests": [
            {
              "timeout": 30000,
              "annotations": [],
              "expectedStatus": "passed",
              "projectId": "chromium",
              "projectName": "chromium",
              "results": [
                {
                  "workerIndex": 1,
                  "status": "passed",
                  "duration": 4558,
                  "errors": [],
                  "stdout": [],
                  "stderr": [],
                  "retry": 0,
                  "startTime": "2024-04-15T05:05:38.887Z",
                  "attachments": []
                }
              ],
              "status": "expected"
            }
          ],
          "id": "dd9b2edffe9b7501040c-f81eb8b32f40aa0da601",
          "file": "example.spec.js",
          "line": 53,
          "column": 6
        }
      ]
    }
  ],
  "errors": [],
  "stats": {
    "startTime": "2024-04-15T05:05:38.020Z",
    "duration": 6415.376,
    "expected": 2,
    "skipped": 0,
    "unexpected": 0,
    "flaky": 0
  }
}